amnish_http_reverse_proxy/__init__.py
amnish_http_reverse_proxy/main.py
amnish_http_reverse_proxy/reverse_proxy.py
amnish_http_reverse_proxy/lib/cache.py
amnish_http_reverse_proxy/lib/load_balancing/round_robin.py
amnish_http_reverse_proxy/utils/__init__.py
amnish_http_reverse_proxy/utils/dummy_server.py
amnish_http_reverse_proxy/utils/logger.py
amnish_http_reverse_proxy-1.0.2.dist-info/METADATA
amnish_http_reverse_proxy-1.0.2.dist-info/WHEEL
amnish_http_reverse_proxy-1.0.2.dist-info/licenses/LICENSE
amnish_http_reverse_proxy-1.0.2.dist-info/RECORD
