Metadata-Version: 2.4
Name: amnish-http-reverse-proxy
Version: 1.0.2
Summary: A secure HTTP reverse proxy supporting features like load-balancing and caching.
Project-URL: Homepage, https://github.com/Amnish04/amnish-http-reverse-proxy
Author-email: Amnish Singh Arora <amnishsingh04@gmail.com>
License-File: LICENSE
Requires-Python: >=3.8
Requires-Dist: flask>=3.1.1
Requires-Dist: python-dotenv>=1.1.1
Requires-Dist: requests>=2.32.4
